{"currentCount":5,"data":[{"감정가금액":125000000,"감정일자":"2018-12-29","개인법인구분":"개인","물건유형":"주거용건물","수임일자":"2019-01-16","이해관계인구분":"소유자","주소":"부산광역시 금정구 남산동"},{"감정가금액":100000000,"감정일자":"2019-10-04","개인법인구분":"개인","물건유형":"주거용건물","수임일자":"2019-10-23","이해관계인구분":"소유자","주소":"울산광역시 울주군 온양읍"},{"감정가금액":256000000,"감정일자":"2019-10-22","개인법인구분":"개인","물건유형":"주거용건물","수임일자":"2019-12-09","이해관계인구분":"소유자","주소":"서울특별시 금천구 시흥동"},{"감정가금액":182500000,"감정일자":"2020-07-12","개인법인구분":"개인","물건유형":"주거용건물","수임일자":"2020-07-30","이해관계인구분":"소유자","주소":"경상북도 경산시 옥곡동"},{"감정가금액":162500000,"감정일자":"2021-07-29","개인법인구분":"개인","물건유형":"주거용건물","수임일자":"2021-08-13","이해관계인구분":"소유자","주소":"강원도 춘천시 퇴계동"}],"matchCount":5,"page":1,"perPage":100,"totalCount":5}
